<Properties StartupConfiguration="{F7584419-5F4D-67ED-0C0C-88CCFC6355A1}|">
  <MonoDevelop.Ide.Workbench ActiveDocument="Assets/Scripts/LevelManager.cs">
    <Files>
      <File FileName="Assets/Scripts/Squid.cs" Line="10" Column="47" />
      <File FileName="Assets/Scripts/Game.cs" Line="75" Column="10" />
      <File FileName="Assets/Scripts/Timer.cs" Line="26" Column="10" />
      <File FileName="Assets/Scripts/Train.cs" Line="10" Column="31" />
      <File FileName="Assets/Scripts/LevelManager.cs" Line="16" Column="9" />
    </Files>
    <Pads>
      <Pad Id="ProjectPad">
        <State name="__root__">
          <Node name="Squid vs Train" expanded="True">
            <Node name="Assets" expanded="True">
              <Node name="Scripts" expanded="True">
                <Node name="LevelManager.cs" selected="True" />
              </Node>
            </Node>
          </Node>
        </State>
      </Pad>
    </Pads>
  </MonoDevelop.Ide.Workbench>
  <MonoDevelop.Ide.DebuggingService.PinnedWatches />
  <MonoDevelop.Ide.Workspace ActiveConfiguration="Debug" />
  <MonoDevelop.Ide.ItemProperties.Assembly-CSharp PreferredExecutionTarget="7961aec0-d59d-4c42-b9da-71b013e892df" />
  <MonoDevelop.Ide.DebuggingService.Breakpoints>
    <BreakpointStore />
  </MonoDevelop.Ide.DebuggingService.Breakpoints>
  <MultiItemStartupConfigurations />
</Properties>